{
  "metadata": {
    "mapbox:groups": {
      "1455204550197.1404": {
        "name": "Stops",
        "collapsed": true
      }
    }
  },
  "sources": {
    "stops": {
      "url": "https://kartat.hsl.fi/jore/tiles/regular-stops/index.json",
      "type": "vector"
    }
  },
  "layers": [
    {
      "id": "Stops case",
      "type": "circle",
      "metadata": {
        "mapbox:group": "1455204550197.1404"
      },
      "source": "stops",
      "source-layer": "stops",
      "interactive": true,
      "filter": [
        "!=",
        "mode",
        "RAIL"
      ],
      "layout": {
        "visibility": "visible"
      },
      "paint": {
        "circle-color": "#fff",
        "circle-radius": {
          "base": 1.15,
          "stops": [
            [
              11.9,
              0
            ],
            [
              12,
              1.5
            ],
            [
              22,
              26
            ]
          ]
        }
      }
    },
    {
      "id": "Stops case rail",
      "type": "circle",
      "metadata": {
        "mapbox:group": "1455204550197.1404"
      },
      "source": "stops",
      "source-layer": "stops",
      "minzoom": 15,
      "interactive": true,
      "filter": [
        "==",
        "mode",
        "RAIL"
      ],
      "layout": {
        "visibility": "visible"
      },
      "paint": {
        "circle-color": "#fff",
        "circle-radius": {
          "base": 1.15,
          "stops": [
            [
              11.9,
              0
            ],
            [
              12,
              1.5
            ],
            [
              22,
              26
            ]
          ]
        }
      }
    },
    {
      "id": "Stops_bus",
      "type": "circle",
      "metadata": {
        "mapbox:group": "1455204550197.1404"
      },
      "source": "stops",
      "source-layer": "stops",
      "interactive": true,
      "filter": [
        "==",
        "mode",
        "BUS"
      ],
      "layout": {
        "visibility": "visible"
      },
      "paint": {
        "circle-color": "#007ac9",
        "circle-radius": {
          "base": 1.15,
          "stops": [
            [
              11.9,
              0
            ],
            [
              12,
              1
            ],
            [
              22,
              24
            ]
          ]
        },
        "circle-opacity": {
          "base": 1,
          "stops": [
            [
              11,
              0.6
            ],
            [
              14,
              1
            ]
          ]
        }
      }
    },
    {
      "id": "Stops_ferry",
      "type": "circle",
      "metadata": {
        "mapbox:group": "1455204550197.1404"
      },
      "source": "stops",
      "source-layer": "stops",
      "interactive": true,
      "filter": [
        "==",
        "mode",
        "FERRY"
      ],
      "layout": {
        "visibility": "visible"
      },
      "paint": {
        "circle-color": "#00b9e4",
        "circle-radius": {
          "base": 1.15,
          "stops": [
            [
              11.9,
              0
            ],
            [
              12,
              1
            ],
            [
              22,
              24
            ]
          ]
        },
        "circle-opacity": {
          "base": 1,
          "stops": [
            [
              11,
              0.6
            ],
            [
              14,
              1
            ]
          ]
        }
      }
    },
    {
      "id": "Stops_tram",
      "type": "circle",
      "metadata": {
        "mapbox:group": "1455204550197.1404"
      },
      "source": "stops",
      "source-layer": "stops",
      "interactive": true,
      "filter": [
        "==",
        "mode",
        "TRAM"
      ],
      "layout": {
        "visibility": "visible"
      },
      "paint": {
        "circle-color": "#00985f",
        "circle-radius": {
          "base": 1.15,
          "stops": [
            [
              11.9,
              0
            ],
            [
              12,
              1
            ],
            [
              22,
              24
            ]
          ]
        },
        "circle-opacity": {
          "base": 1,
          "stops": [
            [
              11,
              0.6
            ],
            [
              14,
              1
            ]
          ]
        }
      }
    },
    {
      "id": "Stops_rail",
      "metadata": {
        "mapbox:group": "1455204550197.1404"
      },
      "ref": "Stops case rail",
      "interactive": true,
      "paint": {
        "circle-color": "#8c54a2",
        "circle-radius": {
          "base": 1.15,
          "stops": [
            [
              11.9,
              0
            ],
            [
              12,
              1
            ],
            [
              22,
              24
            ]
          ]
        },
        "circle-opacity": {
          "base": 1,
          "stops": [
            [
              11,
              0.6
            ],
            [
              14,
              1
            ]
          ]
        }
      }
    },
    {
      "id": "Stops_subway",
      "type": "circle",
      "metadata": {
        "mapbox:group": "1455204550197.1404"
      },
      "source": "stops",
      "source-layer": "stops",
      "interactive": true,
      "filter": [
        "==",
        "mode",
        "SUBWAY"
      ],
      "layout": {
        "visibility": "visible"
      },
      "paint": {
        "circle-color": "#ff6319",
        "circle-radius": {
          "base": 1.15,
          "stops": [
            [
              11.9,
              0
            ],
            [
              12,
              1
            ],
            [
              22,
              24
            ]
          ]
        },
        "circle-opacity": {
          "base": 1,
          "stops": [
            [
              11,
              0.6
            ],
            [
              14,
              1
            ]
          ]
        }
      }
    },
    {
      "id": "Stops_hub",
      "metadata": {
        "mapbox:group": "1455204550197.1404"
      },
      "ref": "Stops case",
      "interactive": true,
      "paint": {
        "circle-color": "#fff",
        "circle-radius": {
          "base": 1.15,
          "stops": [
            [
              14,
              0
            ],
            [
              14.1,
              2
            ],
            [
              22,
              20
            ]
          ]
        }
      }
    },
    {
      "id": "Stops_hub_rail",
      "type": "circle",
      "metadata": {
        "mapbox:group": "1455204550197.1404"
      },
      "source": "stops",
      "source-layer": "stops",
      "minzoom": 15,
      "interactive": true,
      "filter": [
        "in",
        "mode",
        "",
        "RAIL"
      ],
      "layout": {
        "visibility": "visible"
      },
      "paint": {
        "circle-color": "#fff",
        "circle-radius": {
          "base": 1.15,
          "stops": [
            [
              14,
              0
            ],
            [
              14.1,
              2
            ],
            [
              22,
              20
            ]
          ]
        }
      }
    }
  ]
}
